{
    "version": 1,
    "meta": {
        "author": "NMCG",
        "asset": "Multi game object loaded from JSON"
    },
    "spawns": [
        {
            //Main Room Back Wall
            "position": [
                0,
                -0.5,
                -25
            ],
            "rotationDegrees": [
                270,
                0,
                0
            ],
            "scale": [
                0.3065,
                0.3065,
                0.3065
            ],
            "textureName": "WallBrick",
            "modelName": "BigDoorWall",
            "objectName": "spawn-1"
        },
        {
            //Main Room Left Wall
            "position": [
                -24.7,
                -0.5,
                0
            ],
            "rotationDegrees": [
                270,
                0,
                90
            ],
            "scale": [
                0.3065,
                0.3065,
                0.3065
            ],
            "textureName": "WallBrick",
            "modelName": "DoorWall",
            "objectName": "spawn-2"
        },
        {
            //Main Room Right Wall
            "position": [
                24.75,
                -0.5,
                0
            ],
            "rotationDegrees": [
                -90,
                270,
                0
            ],
            "scale": [
                0.3065,
                0.3065,
                0.3065
            ],
            "textureName": "WallBrick",
            "modelName": "DoorWall",
            "objectName": "spawn-3"
        },
        {
            //Main Room Front Wall
            "position": [
                0,
                14.5,
                25
            ],
            "rotationDegrees": [
                180,
                180,
                0
            ],
            "scale": [
                25.1,
                14.9,
                0.74
            ],
            "textureName": "WallBrick",
            "modelName": "BlankWall",
            "objectName": "spawn-4"
        },
        {
            //Khaslana Room Left Wall
            "position": [
                -25.75,
                14.5,
                -50
            ],
            "rotationDegrees": [
                0,
                -90,
                0
            ],
            "scale": [
                24.26,
                14.9,
                0.74
            ],
            "textureName": "WallBrick",
            "modelName": "BlankWall",
            "objectName": "spawn-5"
        },
        {
            //Khaslana Room Right Wall
            "position": [
                25.75,
                14.5,
                -50
            ],
            "rotationDegrees": [
                0,
                90,
                0
            ],
            "scale": [
                24.26,
                14.9,
                0.74
            ],
            "textureName": "WallBrick",
            "modelName": "BlankWall",
            "objectName": "spawn-6"
        },
        {
            //Khaslana Room Back Wall
            "position": [
                0,
                14.5,
                -75
            ],
            "rotationDegrees": [
                0,
                180,
                0
            ],
            "scale": [
                25.1,
                14.9,
                0.74
            ],
            "textureName": "WallBrick",
            "modelName": "BlankWall",
            "objectName": "spawn-7"
        },
        //{
        //Middle Piece
        //"position": [
        //   0,
        //  0,
        //  0
        // ],
        // "rotationDegrees": [
        //   270,
        //   0,
        //    0
        //  ],
        //  "scale": [
        //     -8,
        //     -8,
        //     0.5
        //  ],
        // "textureName": "WallBrick",
        //  "modelName": "MiddlePiece",
        //   "objectName": "spawn-9"
        // },
        {
            //Left Rooms Front Wall
            "position": [
                -42.85,
                14.5,
                25
            ],
            "rotationDegrees": [
                180,
                180,
                0
            ],
            "scale": [
                16.4,
                14.9,
                0.74
            ],
            "textureName": "WallBrick",
            "modelName": "BlankWall",
            "objectName": "spawn-8"
        },
        {
            //Left Room Back Wall
            "position": [
                -42.85,
                14.5,
                -25
            ],
            "rotationDegrees": [
                0,
                180,
                0
            ],
            "scale": [
                16.4,
                14.9,
                0.74
            ],
            "textureName": "WallBrick",
            "modelName": "BlankWall",
            "objectName": "spawn-9"
        },
        {
            //Left Rooms Left Wall
            "position": [
                -60,
                14.5,
                0
            ],
            "rotationDegrees": [
                0,
                -90,
                0
            ],
            "scale": [
                25.1,
                14.9,
                0.74
            ],
            "textureName": "WallBrick",
            "modelName": "BlankWall",
            "objectName": "spawn-10"
        },
        {
            //Left Rooms Wall Divider
            "position": [
                -42.85,
                14.5,
                0.01
            ],
            "rotationDegrees": [
                0,
                180,
                0
            ],
            "scale": [
                16.4,
                14.9,
                0.74
            ],
            "textureName": "WallBrick",
            "modelName": "BlankWall",
            "objectName": "spawn-11"
        },
        {
            //Right Rooms Front Wall
            "position": [
                42.85,
                14.5,
                25
            ],
            "rotationDegrees": [
                180,
                180,
                0
            ],
            "scale": [
                16.4,
                14.9,
                0.74
            ],
            "textureName": "WallBrick",
            "modelName": "BlankWall",
            "objectName": "spawn-12"
        },
        {
            //Right Room Back Wall
            "position": [
                42.85,
                14.5,
                -25
            ],
            "rotationDegrees": [
                0,
                180,
                0
            ],
            "scale": [
                16.4,
                14.9,
                0.74
            ],
            "textureName": "WallBrick",
            "modelName": "BlankWall",
            "objectName": "spawn-13"
        },
        {
            //Right Rooms Left Wall
            "position": [
                60,
                14.5,
                0
            ],
            "rotationDegrees": [
                0,
                -90,
                0
            ],
            "scale": [
                25.1,
                14.9,
                0.74
            ],
            "textureName": "WallBrick",
            "modelName": "BlankWall",
            "objectName": "spawn-14"
        },
        {
            //Right Rooms Wall Divider
            "position": [
                42.85,
                14.5,
                0
            ],
            "rotationDegrees": [
                0,
                180,
                0
            ],
            "scale": [
                16.4,
                14.9,
                0.74
            ],
            "textureName": "WallBrick",
            "modelName": "BlankWall",
            "objectName": "spawn-15"
        },
        {
            //Ceiling Main Room
            "position": [
                0,
                29.89,
                0
            ],
            "rotationDegrees": [
                -90,
                0,
                0
            ],
            "scale": [
                15,
                15,
                0.5
            ],
            "textureName": "WallBrick",
            "modelName": "CeilingMainRoom",
            "objectName": "spawn-16"
        },
        {
            //Ceiling Left Rooms
            "position": [
                -43.5,
                29.4,
                0
            ],
            "rotationDegrees": [
                -90,
                0,
                0
            ],
            "scale": [
                0.34,
                0.5,
                0.5
            ],
            "textureName": "WallBrick",
            "modelName": "CeilingRooms",
            "objectName": "spawn-17"
        },
        {
            //Ceiling Right Rooms
            "position": [
                43.5,
                29.4,
                0
            ],
            "rotationDegrees": [
                -90,
                0,
                0
            ],
            "scale": [
                0.34,
                0.5,
                0.5
            ],
            "textureName": "WallBrick",
            "modelName": "CeilingRooms",
            "objectName": "spawn-18"
        },
        {
            //Ceiling Khaslana Room
            "position": [
                0,
                29.4,
                -50
            ],
            "rotationDegrees": [
                -90,
                0,
                0
            ],
            "scale": [
                0.5,
                0.48,
                0.5
            ],
            "textureName": "WallBrick",
            "modelName": "CeilingRooms",
            "objectName": "spawn-18"
        }
    ]
}

